annsel/__init__.py
annsel/core/__init__.py
annsel/core/expr.py
annsel/core/extensions.py
annsel/core/typing.py
annsel/core/utils.py
annsel/datasets/__init__.py
annsel/datasets/basic.py
annsel/tl/__init__.py
annsel/tl/_filter.py
annsel/tl/_group_by.py
annsel/tl/_select.py
annsel/tl/anndata.py
annsel-0.1.2.dist-info/METADATA
annsel-0.1.2.dist-info/WHEEL
annsel-0.1.2.dist-info/licenses/LICENSE
annsel-0.1.2.dist-info/RECORD
