Metadata-Version: 2.4
Name: annsel
Version: 0.1.2
Summary: A Narwhals powered DataFrame-style selection, filtering and indexing operations on AnnData Objects.
Project-URL: Documentation, https://annsel.readthedocs.io/
Project-URL: Homepage, https://github.com/srivarra/annsel
Project-URL: Source, https://github.com/srivarra/annsel
Author: Sricharan Reddy Varra
Maintainer-email: Sricharan Reddy Varra <srivarra@stanford.edu>
License: MIT License
License-File: LICENSE
Classifier: License :: OSI Approved :: MIT License
Classifier: Programming Language :: Python :: 3 :: Only
Classifier: Programming Language :: Python :: 3.10
Classifier: Programming Language :: Python :: 3.11
Classifier: Programming Language :: Python :: 3.12
Classifier: Programming Language :: Python :: 3.13
Classifier: Topic :: Scientific/Engineering :: Bio-Informatics
Requires-Python: >=3.10
Requires-Dist: anndata
Requires-Dist: more-itertools>=10.7
Requires-Dist: narwhals[pandas]>=2.14
Requires-Dist: pooch>=1.8.2
Requires-Dist: session-info2
Requires-Dist: tqdm>=4
Requires-Dist: universal-pathlib>=0.2
Provides-Extra: dev
Requires-Dist: esbonio>=0.16.5; extra == 'dev'
Requires-Dist: pre-commit; extra == 'dev'
Provides-Extra: doc
Requires-Dist: docutils>=0.21.2; extra == 'doc'
Requires-Dist: ipykernel; extra == 'doc'
Requires-Dist: ipython; extra == 'doc'
Requires-Dist: llvmlite>=0.44.0rc2; extra == 'doc'
Requires-Dist: matplotlib>=3.10; extra == 'doc'
Requires-Dist: myst-nb>=1.1.2; extra == 'doc'
Requires-Dist: numba>=0.61.0rc2; extra == 'doc'
Requires-Dist: pandas; extra == 'doc'
Requires-Dist: polars; extra == 'doc'
Requires-Dist: pyarrow; extra == 'doc'
Requires-Dist: scanpy>=1.11.0rc1; extra == 'doc'
Requires-Dist: scanpydoc>=0.15.2; extra == 'doc'
Requires-Dist: setuptools; extra == 'doc'
Requires-Dist: sphinx-autodoc-typehints; extra == 'doc'
Requires-Dist: sphinx-autosummary-accessors>=2023.4; extra == 'doc'
Requires-Dist: sphinx-book-theme>=1.1.3; extra == 'doc'
Requires-Dist: sphinx-copybutton; extra == 'doc'
Requires-Dist: sphinx-design>=0.6.1; extra == 'doc'
Requires-Dist: sphinx-tabs; extra == 'doc'
Requires-Dist: sphinx-toolbox; extra == 'doc'
Requires-Dist: sphinx<8.2,>=8.1.3; extra == 'doc'
Requires-Dist: sphinxcontrib-bibtex>=2.6.3; extra == 'doc'
Requires-Dist: sphinxext-opengraph; extra == 'doc'
Provides-Extra: nb
Requires-Dist: jupyterlab>=4.3.4; extra == 'nb'
Provides-Extra: test
Requires-Dist: coverage; extra == 'test'
Requires-Dist: pytest; extra == 'test'
Requires-Dist: pytest-cov>=6; extra == 'test'
Requires-Dist: pytest-xdist>=3.6.1; extra == 'test'
